<?xml version="1.0" encoding="UTF-8"?>
<feature
      id="org.nakeduml.uim.feature"
      label="User Interaction Modelling"
      version="1.0.0.qualifier"
      provider-name="NakedUML">

   <description url="http://www.example.com/description">
      [Enter Feature Description here.]
   </description>

   <copyright url="http://www.example.com/copyright">
      [Enter Copyright Description here.]
   </copyright>

   <license url="http://www.example.com/license">
      [Enter License Description here.]
   </license>

   <requires>
      <import plugin="org.eclipse.core.runtime"/>
      <import plugin="org.eclipse.ui.ide"/>
      <import plugin="org.eclipse.uml2.uml.edit"/>
      <import plugin="org.eclipse.core.resources"/>
      <import plugin="org.eclipse.draw2d"/>
      <import plugin="org.eclipse.emf.edit.ui"/>
      <import plugin="org.eclipse.uml2.uml"/>
      <import plugin="org.topcased.modeler" match="greaterOrEqual"/>
      <import plugin="org.eclipse.ui.views.properties.tabbed"/>
      <import plugin="org.nakeduml.eclipse"/>
      <import plugin="org.eclipse.ui"/>
      <import plugin="org.nakeduml.uim"/>
      <import plugin="org.nakeduml.metamodels"/>
      <import plugin="org.topcased.tabbedproperties"/>
      <import plugin="org.topcased.modeler.diagrams"/>
      <import plugin="org.eclipse.emf.edit"/>
      <import plugin="org.eclipse.emf.ecore"/>
      <import plugin="org.eclipse.emf.ecore.edit"/>
      <import plugin="org.nakeduml.generators"/>
      <import plugin="org.nakeduml.java.generator"/>
      <import plugin="org.nakeduml.java.metamodel"/>
      <import plugin="org.nakeduml.ocl.java.generator"/>
      <import plugin="org.nakeduml.ocl.metamodel"/>
   </requires>

   <plugin
         id="org.nakeduml.uim.classform"
         download-size="0"
         install-size="0"
         version="0.0.0"
         unpack="false"/>

   <plugin
         id="org.nakeduml.uim.editor"
         download-size="0"
         install-size="0"
         version="0.0.0"
         unpack="false"/>

   <plugin
         id="org.nakeduml.uim.modeleditor"
         download-size="0"
         install-size="0"
         version="0.0.0"
         unpack="false"/>

   <plugin
         id="org.nakeduml.uim.uml2uim"
         download-size="0"
         install-size="0"
         version="0.0.0"
         unpack="false"/>

   <plugin
         id="org.nakeduml.uim.userinteractionproperties"
         download-size="0"
         install-size="0"
         version="0.0.0"
         unpack="false"/>

   <plugin
         id="org.nakeduml.uim2uim.actions"
         download-size="0"
         install-size="0"
         version="0.0.0"
         unpack="false"/>

   <plugin
         id="org.nakeduml.uim.edit"
         download-size="0"
         install-size="0"
         version="0.0.0"
         unpack="false"/>

</feature>
